pyams_skin/__init__.py
pyams_skin/include.py
pyams_skin/metas.py
pyams_skin/doctests/README.rst
pyams_skin/doctests/metas.rst
pyams_skin/interfaces/__init__.py
pyams_skin/interfaces/form.py
pyams_skin/interfaces/metas.py
pyams_skin/interfaces/schema.py
pyams_skin/interfaces/view.py
pyams_skin/interfaces/viewlet.py
pyams_skin/interfaces/widget.py
pyams_skin/interfaces/templates/bootstrap-devices-display.pt
pyams_skin/interfaces/templates/bootstrap-devices-input.pt
pyams_skin/interfaces/templates/bootstrap-selection-display.pt
pyams_skin/interfaces/templates/bootstrap-selection-input.pt
pyams_skin/interfaces/templates/button-display.pt
pyams_skin/interfaces/templates/button-input.pt
pyams_skin/interfaces/templates/checkbox-display.pt
pyams_skin/interfaces/templates/checkbox-input.pt
pyams_skin/interfaces/templates/close-display.pt
pyams_skin/interfaces/templates/close-input.pt
pyams_skin/interfaces/templates/color-display.pt
pyams_skin/interfaces/templates/color-input.pt
pyams_skin/interfaces/templates/date-display.pt
pyams_skin/interfaces/templates/date-input.pt
pyams_skin/interfaces/templates/dates-range-display.pt
pyams_skin/interfaces/templates/dates-range-input.pt
pyams_skin/interfaces/templates/datetime-display.pt
pyams_skin/interfaces/templates/datetime-input.pt
pyams_skin/interfaces/templates/form-display.pt
pyams_skin/interfaces/templates/form-group.pt
pyams_skin/interfaces/templates/form-tabform.pt
pyams_skin/interfaces/templates/form.pt
pyams_skin/interfaces/templates/fullpage-modal-layout.pt
pyams_skin/interfaces/templates/html-display.pt
pyams_skin/interfaces/templates/html-input.pt
pyams_skin/interfaces/templates/http-method-display.pt
pyams_skin/interfaces/templates/http-method-input.pt
pyams_skin/interfaces/templates/inner-layout.pt
pyams_skin/interfaces/templates/modal-layout.pt
pyams_skin/interfaces/templates/object-display.pt
pyams_skin/interfaces/templates/object-input.pt
pyams_skin/interfaces/templates/object-layout.pt
pyams_skin-2.4.1.dist-info/LICENSE
pyams_skin-2.4.1.dist-info/METADATA
pyams_skin-2.4.1.dist-info/WHEEL
pyams_skin-2.4.1.dist-info/namespace_packages.txt
pyams_skin-2.4.1.dist-info/top_level.txt
pyams_skin-2.4.1.dist-info/RECORD
