Metadata-Version: 2.1
Name: pyams-skin
Version: 2.4.1
Summary: PyAMS base skin management features
Home-page: https://pyams.readthedocs.io
Author: Thierry Florac
Author-email: tflorac@ulthar.net
License: ZPL
Keywords: Pyramid PyAMS
Classifier: License :: OSI Approved :: Zope Public License
Classifier: Development Status :: 4 - Beta
Classifier: Programming Language :: Python
Classifier: Framework :: Pyramid
Classifier: Topic :: Software Development :: Libraries :: Python Modules
Requires-Python: >=3.7
License-File: LICENSE
Requires-Dist: setuptools
Requires-Dist: pyams-file
Requires-Dist: pyams-form
Requires-Dist: pyams-layer
Requires-Dist: pyams-template
Requires-Dist: pyams-utils >=2.7.7
Requires-Dist: pyams-viewlet
Requires-Dist: pyramid >=2.0.0
Requires-Dist: zope.component
Requires-Dist: zope.interface
Requires-Dist: zope.schema
Provides-Extra: test
Requires-Dist: pyramid-zcml ; extra == 'test'
Requires-Dist: zope.exceptions ; extra == 'test'
